{"asset/examples/european.jpg":["asset/examples/european.jpg"],"asset/examples/gothic.jpg":["asset/examples/gothic.jpg"],"asset/examples/islamic.jpg":["asset/examples/islamic.jpg"],"asset/examples/japanese.jpeg":["asset/examples/japanese.jpeg"],"asset/examples/japanese.jpg":["asset/examples/japanese.jpg"],"asset/examples/modern.jpg":["asset/examples/modern.jpg"],"asset/examples/nature.jpg":["asset/examples/nature.jpg"],"asset/examples/roman.jpg":["asset/examples/roman.jpg"],"asset/fonts/AnthoniaSignature.ttf":["asset/fonts/AnthoniaSignature.ttf"],"asset/fonts/ArabicRamadan.ttf":["asset/fonts/ArabicRamadan.ttf"],"asset/fonts/Canterbury.ttf":["asset/fonts/Canterbury.ttf"],"asset/fonts/NaturalForestDemoRegular.ttf":["asset/fonts/NaturalForestDemoRegular.ttf"],"asset/fonts/SamuraiBlast.ttf":["asset/fonts/SamuraiBlast.ttf"],"asset/fonts/ZenDots-Regular.ttf":["asset/fonts/ZenDots-Regular.ttf"],"asset/under_development/wallpaper.gif":["asset/under_development/wallpaper.gif"],"asset/under_development/wallpaper.png":["asset/under_development/wallpaper.png"],"packages/cupertino_icons/assets/CupertinoIcons.ttf":["packages/cupertino_icons/assets/CupertinoIcons.ttf"]}